AoiSora
setup.py
aoisora/__init__.py
aoisora/window.py
aoisora.egg-info/PKG-INFO
aoisora.egg-info/SOURCES.txt
aoisora.egg-info/dependency_links.txt
aoisora.egg-info/top_level.txt
aoisora/device/__init__.py
aoisora/device/item.py
aoisora/device/mixin.py
aoisora/device/thread.py
aoisora/device/tree.py