Metadata-Version: 1.1
Name: aoisora
Version: 0.0.2
Summary: Lightweight Bluetooth manager for Bluez5 with PyQt4 UI
Home-page: https://pypi.python.org/pypi/aoisora
Author: Okami
Author-email: okami@fuzetsu.info
License: GPLv3
Keywords: bluetooth bluez pyqt
Platform: UNKNOWN
Classifier: Development Status :: 3 - Alpha
Classifier: Programming Language :: Python :: 3
Classifier: License :: OSI Approved :: GNU General Public License v3 or later (GPLv3+)
